core/__init__.py
core/sstable.py
core/sstable_builder.py
core/sstable_partition.py
py_sstable-0.1.1.data/data/lib/libsstable_internal.so
test/__init__.py
test/test_sstable.py
test/test_sstable_partition.py
py_sstable-0.1.1.dist-info/METADATA
py_sstable-0.1.1.dist-info/WHEEL
py_sstable-0.1.1.dist-info/top_level.txt
py_sstable-0.1.1.dist-info/RECORD
